choline/__init__.py
choline/choline.py
choline/utils.py
choline/commands/__init__.py
choline/commands/code.py
choline/commands/init.py
choline/commands/kill.py
choline/commands/launch.py
choline/commands/monitor_and_setup_machine.py
choline/commands/repeat.py
choline/commands/status.py
choline/commands/stream.py
choline/commands/sync.py
choline-0.1.dist-info/METADATA
choline-0.1.dist-info/WHEEL
choline-0.1.dist-info/entry_points.txt
choline-0.1.dist-info/top_level.txt
choline-0.1.dist-info/RECORD
