Metadata-Version: 2.1
Name: choline
Version: 0.1
Requires-Dist: paramiko
Requires-Dist: scp
Requires-Dist: PyYAML
Requires-Dist: torch
Requires-Dist: vastai
